ultimatevocalremover/UVR.py
ultimatevocalremover/__init__.py
ultimatevocalremover/__version__.py
ultimatevocalremover/demucs/__init__.py
ultimatevocalremover/demucs/__main__.py
ultimatevocalremover/demucs/apply.py
ultimatevocalremover/demucs/demucs.py
ultimatevocalremover/demucs/filtering.py
ultimatevocalremover/demucs/hdemucs.py
ultimatevocalremover/demucs/htdemucs.py
ultimatevocalremover/demucs/model.py
ultimatevocalremover/demucs/model_v2.py
ultimatevocalremover/demucs/pretrained.py
ultimatevocalremover/demucs/repo.py
ultimatevocalremover/demucs/spec.py
ultimatevocalremover/demucs/states.py
ultimatevocalremover/demucs/tasnet.py
ultimatevocalremover/demucs/tasnet_v2.py
ultimatevocalremover/demucs/transformer.py
ultimatevocalremover/demucs/utils.py
ultimatevocalremover/gui_data/app_size_values.py
ultimatevocalremover/gui_data/change_log.txt
ultimatevocalremover/gui_data/complete_chime.wav
ultimatevocalremover/gui_data/constants.py
ultimatevocalremover/gui_data/error_handling.py
ultimatevocalremover/gui_data/fail_chime.wav
ultimatevocalremover/gui_data/fonts/Montserrat/Montserrat.ttf
ultimatevocalremover/gui_data/fonts/centurygothic/GOTHIC.ttf
ultimatevocalremover/gui_data/fonts/other/own_font_goes_here.txt
ultimatevocalremover/gui_data/img/File.png
ultimatevocalremover/gui_data/img/GUI-Icon.ico
ultimatevocalremover/gui_data/img/GUI-Icon.png
ultimatevocalremover/gui_data/img/UVR-banner.png
ultimatevocalremover/gui_data/img/UVR.icns
ultimatevocalremover/gui_data/img/UVR_v5.6.png
ultimatevocalremover/gui_data/img/clear.png
ultimatevocalremover/gui_data/img/copy.png
ultimatevocalremover/gui_data/img/credits.png
ultimatevocalremover/gui_data/img/donate.png
ultimatevocalremover/gui_data/img/down.png
ultimatevocalremover/gui_data/img/download.png
ultimatevocalremover/gui_data/img/help.png
ultimatevocalremover/gui_data/img/key.png
ultimatevocalremover/gui_data/img/left.png
ultimatevocalremover/gui_data/img/pause.png
ultimatevocalremover/gui_data/img/play.png
ultimatevocalremover-5.6.1.dist-info/METADATA
ultimatevocalremover-5.6.1.dist-info/WHEEL
ultimatevocalremover-5.6.1.dist-info/entry_points.txt
ultimatevocalremover-5.6.1.dist-info/RECORD
