Metadata-Version: 2.1
Name: ultimatevocalremover
Version: 5.6.1
Summary: 
Author: Anjok07
Author-email: 68268275+Anjok07@users.noreply.github.com
Requires-Python: >=3.10,<4.0.0
Classifier: Programming Language :: Python :: 3
Classifier: Programming Language :: Python :: 3.10
Classifier: Programming Language :: Python :: 3.11
Requires-Dist: altgraph (==0.17.3)
Requires-Dist: audioread (==3.0.0)
Requires-Dist: certifi (==2022.12.07)
Requires-Dist: cffi (==1.15.1)
Requires-Dist: cryptography (==3.4.6)
Requires-Dist: diffq (>=0.2.4,<0.3.0)
Requires-Dist: einops (==0.6.0)
Requires-Dist: future (==0.18.3)
Requires-Dist: julius (==0.2.7)
Requires-Dist: kthread (==0.2.3)
Requires-Dist: librosa (==0.9.2)
Requires-Dist: llvmlite (>=0.41.1,<0.42.0)
Requires-Dist: matchering (==2.0.6)
Requires-Dist: ml-collections (==0.1.1)
Requires-Dist: natsort (==8.2.0)
Requires-Dist: numpy (==1.23.5)
Requires-Dist: omegaconf (==2.2.3)
Requires-Dist: onnx (>=1.15.0,<2.0.0)
Requires-Dist: onnx2pytorch (>=0.4.1,<0.5.0)
Requires-Dist: onnxruntime (>=1.16.3,<2.0.0)
Requires-Dist: opencv-python (==4.6.0.66)
Requires-Dist: pillow (==9.3.0)
Requires-Dist: psutil (==5.9.4)
Requires-Dist: pydub (==0.25.1)
Requires-Dist: pyglet (==1.5.23)
Requires-Dist: pyperclip (==1.8.2)
Requires-Dist: pyrubberband (==0.3.0)
Requires-Dist: pysoundfile (==0.9.0.post1) ; sys_platform == "darwin"
Requires-Dist: pytorch-lightning (==2.0.0)
Requires-Dist: pyyaml (==6.0)
Requires-Dist: resampy (==0.4.2)
Requires-Dist: samplerate (==0.1.0)
Requires-Dist: scipy (==1.9.3)
Requires-Dist: screeninfo (==0.8.1)
Requires-Dist: soundfile (==0.11.0) ; sys_platform != "darwin"
Requires-Dist: soundstretch (==1.2)
Requires-Dist: torch (>=2.1.2,<3.0.0)
Requires-Dist: urllib3 (==1.26.12)
Requires-Dist: wget (==3.2)
